ear/__init__.py
ear_transformers-1.0.1.dist-info/LICENSE.md
ear_transformers-1.0.1.dist-info/METADATA
ear_transformers-1.0.1.dist-info/WHEEL
ear_transformers-1.0.1.dist-info/top_level.txt
ear_transformers-1.0.1.dist-info/RECORD
