Metadata-Version: 2.1
Name: ear-transformers
Version: 1.0.1
Summary: Entropy-based Attention Regularization
Home-page: https://github.com/g8a9/ear
Author: Giuseppe Attanasio
Author-email: giuseppeattanasio6@gmail.com
License: MIT
Platform: UNKNOWN
Classifier: License :: OSI Approved :: MIT License
Classifier: Programming Language :: Python :: 3
Classifier: Programming Language :: Python :: 3.7
License-File: LICENSE.md
Requires-Dist: transformers
